dataframe_expectations/__init__.py
dataframe_expectations/logging_utils.py
dataframe_expectations/registry.py
dataframe_expectations/result_message.py
dataframe_expectations/suite.py
dataframe_expectations/suite.pyi
dataframe_expectations/core/__init__.py
dataframe_expectations/core/aggregation_expectation.py
dataframe_expectations/core/column_expectation.py
dataframe_expectations/core/expectation.py
dataframe_expectations/core/types.py
dataframe_expectations/core/utils.py
dataframe_expectations/expectations/__init__.py
dataframe_expectations/expectations/aggregation/__init__.py
dataframe_expectations/expectations/aggregation/any_value.py
dataframe_expectations/expectations/aggregation/numerical.py
dataframe_expectations/expectations/aggregation/unique.py
dataframe_expectations/expectations/column/__init__.py
dataframe_expectations/expectations/column/any_value.py
dataframe_expectations/expectations/column/numerical.py
dataframe_expectations/expectations/column/string.py
dataframe_expectations-0.4.0.dist-info/licenses/LICENSE.txt
dataframe_expectations-0.4.0.dist-info/METADATA
dataframe_expectations-0.4.0.dist-info/WHEEL
dataframe_expectations-0.4.0.dist-info/top_level.txt
dataframe_expectations-0.4.0.dist-info/RECORD
