Metadata-Version: 2.4
Name: dataframe-expectations
Version: 0.4.0
Summary: Python library designed to validate Pandas and PySpark DataFrames using customizable, reusable expectations
Author-email: Data Products GetYourGuide <engineering.data-products@getyourguide.com>
Requires-Python: >=3.10
License-File: LICENSE.txt
Requires-Dist: pandas>=1.5.0
Requires-Dist: pydantic>=2.12.4
Requires-Dist: pyspark>=3.3.0
Requires-Dist: tabulate>=0.8.9
Dynamic: license-file
